parfold/__init__.py
parfold/bst.py
parfold/primitives.py
parfold/py.typed
parfold/sort.py
parfold-0.1.3.dist-info/METADATA
parfold-0.1.3.dist-info/WHEEL
parfold-0.1.3.dist-info/licenses/LICENSE
parfold-0.1.3.dist-info/RECORD
