Metadata-Version: 2.4
Name: parfold
Version: 0.1.3
Summary: Parallel async primitives: fold, unfold, map, filter, and sorting
Project-URL: Homepage, https://github.com/doublewordai/parfold
Project-URL: Repository, https://github.com/doublewordai/parfold
Project-URL: Issues, https://github.com/doublewordai/parfold/issues
Author-email: Doubleword AI <hello@doubleword.ai>
License-Expression: MIT
License-File: LICENSE
Keywords: async,fold,parallel,primitives,reduce,tree,unfold
Classifier: Development Status :: 4 - Beta
Classifier: Framework :: AsyncIO
Classifier: Intended Audience :: Developers
Classifier: License :: OSI Approved :: MIT License
Classifier: Programming Language :: Python :: 3
Classifier: Programming Language :: Python :: 3.10
Classifier: Programming Language :: Python :: 3.11
Classifier: Programming Language :: Python :: 3.12
Classifier: Programming Language :: Python :: 3.13
Classifier: Typing :: Typed
Requires-Python: >=3.10
Provides-Extra: test
Requires-Dist: pytest-asyncio>=0.21; extra == 'test'
Requires-Dist: pytest>=7.0; extra == 'test'
